gcode_mass_matrix_analyzer/__init__.py
gcode_mass_matrix_analyzer/__main__.py
gcode_mass_matrix_analyzer/analyzer.py
gcode_mass_matrix_analyzer-1.0.0.dist-info/licenses/LICENSE
gcode_mass_matrix_analyzer-1.0.0.dist-info/METADATA
gcode_mass_matrix_analyzer-1.0.0.dist-info/WHEEL
gcode_mass_matrix_analyzer-1.0.0.dist-info/entry_points.txt
gcode_mass_matrix_analyzer-1.0.0.dist-info/top_level.txt
gcode_mass_matrix_analyzer-1.0.0.dist-info/RECORD
