Metadata-Version: 2.4
Name: gcode-mass-matrix-analyzer
Version: 1.0.0
Summary: Extract mass matrices from 3D printer G-code files
Author-email: GitHub Copilot and Boya <noreply@github.com>
Project-URL: Homepage, https://github.com/your-username/gcode-mass-matrix-analyzer
Project-URL: Repository, https://github.com/your-username/gcode-mass-matrix-analyzer
Project-URL: Issues, https://github.com/your-username/gcode-mass-matrix-analyzer/issues
Project-URL: Documentation, https://github.com/your-username/gcode-mass-matrix-analyzer#readme
Keywords: 3d-printing,gcode,mass-matrix,inertia,bambulab,3d-printer
Classifier: Development Status :: 4 - Beta
Classifier: Intended Audience :: Developers
Classifier: Intended Audience :: Science/Research
Classifier: Operating System :: OS Independent
Classifier: Programming Language :: Python :: 3
Classifier: Programming Language :: Python :: 3.7
Classifier: Programming Language :: Python :: 3.8
Classifier: Programming Language :: Python :: 3.9
Classifier: Programming Language :: Python :: 3.10
Classifier: Programming Language :: Python :: 3.11
Classifier: Programming Language :: Python :: 3.12
Classifier: Topic :: Scientific/Engineering
Classifier: Topic :: Software Development :: Libraries :: Python Modules
Classifier: Topic :: System :: Hardware :: Hardware Drivers
Requires-Python: >=3.7
License-File: LICENSE
Requires-Dist: numpy>=1.20.0
Provides-Extra: dev
Requires-Dist: pytest>=6.0; extra == "dev"
Requires-Dist: black; extra == "dev"
Requires-Dist: flake8; extra == "dev"
Requires-Dist: mypy; extra == "dev"
Requires-Dist: build; extra == "dev"
Requires-Dist: twine; extra == "dev"
Dynamic: license-file
